{"id":"0112e9af-5129-48ba-af78-92c40ac40b40","revision":0,"last_node_id":109,"last_link_id":140,"nodes":[{"id":9,"type":"CLIPTextEncode","pos":[1348.2760625316118,4362.9653692735965],"size":[400,200],"flags":{"collapsed":true},"order":40,"mode":0,"inputs":[{"label":"CLIP","localized_name":"clip","name":"clip","type":"CLIP","link":71},{"localized_name":"文本","name":"text","type":"STRING","widget":{"name":"text"},"link":null}],"outputs":[{"label":"条件","localized_name":"条件","name":"CONDITIONING","type":"CONDITIONING","links":[18]}],"properties":{"cnr_id":"comfy-core","ver":"0.3.56","Node name for S&R":"CLIPTextEncode","ue_properties":{"widget_ue_connectable":{},"version":"7.5.2","input_ue_unconnectable":{}},"enableTabs":false,"tabWidth":65,"tabXOffset":10,"hasSecondTab":false,"secondTabText":"Send Back","secondTabOffset":80,"secondTabWidth":65},"widgets_values":["blurry, out of focus, overexposed, underexposed, low contrast, washed out colors, excessive noise, grainy texture, poor lighting, flickering, motion blur, distorted proportions, unnatural skin tones, deformed facial features, asymmetrical face, missing facial features, extra limbs, disfigured hands, wrong hand count, artifacts around text, unreadable text on shirt or hat, incorrect lettering on cap (“PNTR”), incorrect t-shirt slogan (“JUST DO IT”), missing microphone, misplaced microphone, inconsistent perspective, camera shake, incorrect depth of field, background too sharp, background clutter, distracting reflections, harsh shadows, inconsistent lighting direction, color banding, cartoonish rendering, 3D CGI look, unrealistic materials, uncanny valley effect, incorrect ethnicity, wrong gender, exaggerated expressions, smiling, laughing, exaggerated sadness, wrong gaze direction, eyes looking at camera, mismatched lip sync, silent or muted audio, distorted voice, robotic voice, echo, background noise, off-sync audio, missing sniff sounds, incorrect dialogue, added dialogue, repetitive speech, jittery movement, awkward pauses, incorrect timing, unnatural transitions, inconsistent framing, tilted camera, missing door or shelves, missing shallow depth of field, flat lighting, inconsistent tone, cinematic oversaturation, stylized filters, or AI artifacts."],"color":"#323","bgcolor":"#535"},{"id":48,"type":"SetNode","pos":[576.5108132071028,4490.218578929788],"size":[210,34],"flags":{"collapsed":true},"order":47,"mode":0,"inputs":[{"name":"VAE","type":"VAE","link":67}],"outputs":[{"label":"输出","name":"*","type":"*","links":null}],"title":"Set_VAE","properties":{"previousName":"","ue_properties":{"widget_ue_connectable":{},"version":"7.5.2","input_ue_unconnectable":{}}},"widgets_values":["vae"],"color":"#322","bgcolor":"#533"},{"id":52,"type":"SetNode","pos":[541.451967851586,3701.154084943116],"size":[210,60],"flags":{"collapsed":true},"order":63,"mode":0,"inputs":[{"name":"MODEL","type":"MODEL","link":109}],"outputs":[{"label":"输出","name":"*","type":"*","links":null}],"title":"Set_MODEL","properties":{"previousName":"model","ue_properties":{"widget_ue_connectable":{},"version":"7.5.2","input_ue_unconnectable":{}}},"widgets_values":["model"],"color":"#223","bgcolor":"#335"},{"id":58,"type":"SetNode","pos":[702.4139134133129,4698.801285977129],"size":[210,34],"flags":{"collapsed":true},"order":43,"mode":0,"inputs":[{"name":"INT","type":"INT","link":78}],"outputs":[{"label":"输出","name":"*","type":"*","links":null}],"title":"Set_INT","properties":{"previousName":"","ue_properties":{"widget_ue_connectable":{},"version":"7.5.2","input_ue_unconnectable":{}}},"widgets_values":["height"],"color":"#1b4669","bgcolor":"#29699c"},{"id":59,"type":"SetNode","pos":[469.29141055119203,4707.353470507852],"size":[210,34],"flags":{"collapsed":true},"order":42,"mode":0,"inputs":[{"name":"INT","type":"INT","link":79}],"outputs":[{"label":"输出","name":"*","type":"*","links":null}],"title":"Set_INT","properties":{"previousName":"","ue_properties":{"widget_ue_connectable":{},"version":"7.5.2","input_ue_unconnectable":{}}},"widgets_values":["width"],"color":"#1b4669","bgcolor":"#29699c"},{"id":60,"type":"SetNode","pos":[1161.0698215393263,4694.324951757653],"size":[210,34],"flags":{"collapsed":true},"order":37,"mode":0,"inputs":[{"name":"FLOAT","type":"FLOAT","link":80}],"outputs":[{"label":"输出","name":"*","type":"*","links":null}],"title":"Set_FLOAT","properties":{"previousName":"","ue_properties":{"widget_ue_connectable":{},"version":"7.5.2","input_ue_unconnectable":{}}},"widgets_values":["fps"],"color":"#232","bgcolor":"#353"},{"id":63,"type":"PrimitiveFloat","pos":[1138.490864337175,4682.131972763076],"size":[210,61.42105412153796],"flags":{},"order":0,"mode":0,"inputs":[{"label":"value","localized_name":"值","name":"value","type":"FLOAT","widget":{"name":"value"},"link":null}],"outputs":[{"label":"FLOAT","localized_name":"浮点","name":"FLOAT","type":"FLOAT","links":[80,83]}],"title":"FPS","properties":{"cnr_id":"comfy-core","ver":"0.10.0","Node name for S&R":"PrimitiveFloat","ue_properties":{"widget_ue_connectable":{},"version":"7.5.2","input_ue_unconnectable":{}}},"widgets_values":[24],"color":"#006691","bgcolor":"rgba(24,24,27,.9)"},{"id":64,"type":"SetNode","pos":[939.9759637999416,4708.1903381773245],"size":[210,34],"flags":{"collapsed":true},"order":56,"mode":0,"inputs":[{"name":"INT","type":"INT","link":81}],"outputs":[{"label":"输出","name":"*","type":"*","links":null}],"title":"Set_INT","properties":{"previousName":"","ue_properties":{"widget_ue_connectable":{},"version":"7.5.2","input_ue_unconnectable":{}}},"widgets_values":["frames"],"color":"#1b4669","bgcolor":"#29699c"},{"id":65,"type":"SimpleCalculatorKJ","pos":[899.0271590672317,4710.433568480609],"size":[210,108],"flags":{"collapsed":true},"order":49,"mode":0,"inputs":[{"label":"a","localized_name":"variables.a","name":"variables.a","shape":7,"type":"INT,FLOAT,BOOLEAN","link":null},{"label":"b","localized_name":"variables.b","name":"variables.b","shape":7,"type":"INT,FLOAT,BOOLEAN","link":null},{"label":"expression","localized_name":"expression","name":"expression","type":"STRING","widget":{"name":"expression"},"link":null},{"label":"a","localized_name":"a","name":"a","shape":7,"type":"*","link":82},{"label":"b","localized_name":"b","name":"b","shape":7,"type":"*","link":83}],"outputs":[{"label":"FLOAT","localized_name":"浮点","name":"FLOAT","type":"FLOAT","links":[]},{"label":"INT","localized_name":"整数","name":"INT","type":"INT","links":[81]},{"localized_name":"布尔","name":"BOOLEAN","type":"BOOLEAN","links":null}],"properties":{"cnr_id":"comfyui-kjnodes","ver":"17cddd4959f00182c66954be2a7a32a6481d81be","Node name for S&R":"SimpleCalculatorKJ","ue_properties":{"widget_ue_connectable":{},"version":"7.5.2","input_ue_unconnectable":{}}},"widgets_values":["1+ 8*(round(a*b)/8)"],"color":"#006691","bgcolor":"rgba(24,24,27,.9)"},{"id":68,"type":"SetNode","pos":[1519.3877289290585,4708.230575823328],"size":[210,34],"flags":{"collapsed":true},"order":51,"mode":0,"inputs":[{"name":"BOOLEAN","type":"BOOLEAN","link":84}],"outputs":[{"label":"输出","name":"*","type":"*","links":null}],"title":"Set_BOOLEAN","properties":{"previousName":"","ue_properties":{"widget_ue_connectable":{},"version":"7.5.2","input_ue_unconnectable":{}}},"widgets_values":["t2v_mode"]},{"id":72,"type":"GetNode","pos":[929.8310589181082,4331.315987765174],"size":[210,58],"flags":{"collapsed":true},"order":1,"mode":0,"inputs":[],"outputs":[{"name":"INT","type":"INT","links":[85]}],"properties":{"ue_properties":{"widget_ue_connectable":{},"version":"7.5.2","input_ue_unconnectable":{}}},"widgets_values":["height"],"color":"#1b4669","bgcolor":"#29699c"},{"id":75,"type":"SimpleCalculatorKJ","pos":[1740.5622917924213,3713.108353502049],"size":[275.56750142828105,108],"flags":{"collapsed":true},"order":38,"mode":0,"inputs":[{"label":"a","localized_name":"variables.a","name":"variables.a","shape":7,"type":"INT,FLOAT,BOOLEAN","link":null},{"label":"b","localized_name":"variables.b","name":"variables.b","shape":7,"type":"INT,FLOAT,BOOLEAN","link":null},{"label":"expression","localized_name":"expression","name":"expression","type":"STRING","widget":{"name":"expression"},"link":null},{"label":"a","localized_name":"a","name":"a","shape":7,"type":"*","link":92},{"label":"b","localized_name":"b","name":"b","shape":7,"type":"*","link":null}],"outputs":[{"label":"FLOAT","localized_name":"浮点","name":"FLOAT","type":"FLOAT","links":null},{"label":"INT","localized_name":"整数","name":"INT","type":"INT","links":[93]},{"localized_name":"布尔","name":"BOOLEAN","type":"BOOLEAN","links":null}],"title":"float to int","properties":{"cnr_id":"comfyui-kjnodes","ver":"f710f2635dbadbaf1ccf7d25572daa7dfec80bfd","Node name for S&R":"SimpleCalculatorKJ","ue_properties":{"widget_ue_connectable":{},"version":"7.5.2","input_ue_unconnectable":{}}},"widgets_values":["a"]},{"id":74,"type":"GetNode","pos":[1740.5622917924213,3717.66975899743],"size":[275.56750142828105,60],"flags":{"collapsed":true},"order":2,"mode":0,"inputs":[],"outputs":[{"name":"FLOAT","type":"FLOAT","links":[92]}],"properties":{"ue_properties":{"widget_ue_connectable":{},"version":"7.5.2","input_ue_unconnectable":{}}},"widgets_values":["fps"],"color":"#346434","bgcolor":"rgba(24,24,27,.9)"},{"id":53,"type":"GetNode","pos":[1422.7800283235283,4202.983290828403],"size":[210,60],"flags":{"collapsed":true},"order":3,"mode":0,"inputs":[],"outputs":[{"name":"CLIP","type":"CLIP","links":[70,71]}],"properties":{"ue_properties":{"widget_ue_connectable":{},"version":"7.5.2","input_ue_unconnectable":{}}},"widgets_values":["clip"],"color":"#c09430","bgcolor":"rgba(24,24,27,.9)"},{"id":57,"type":"GetNode","pos":[2433.1400328115133,3896.953187856053],"size":[234.124545778805,58],"flags":{"collapsed":true},"order":4,"mode":0,"inputs":[],"outputs":[{"name":"VAE","type":"VAE","links":[75]}],"properties":{"ue_properties":{"widget_ue_connectable":{},"version":"7.5.2","input_ue_unconnectable":{}}},"widgets_values":["vae"],"color":"#af3535","bgcolor":"rgba(24,24,27,.9)"},{"id":44,"type":"DualCLIPLoader","pos":[124.77303075735584,4438.54849380259],"size":[325.8044018136112,130],"flags":{"collapsed":true},"order":5,"mode":0,"inputs":[{"localized_name":"CLIP名称1","name":"clip_name1","type":"COMBO","widget":{"name":"clip_name1"},"link":null},{"localized_name":"CLIP名称2","name":"clip_name2","type":"COMBO","widget":{"name":"clip_name2"},"link":null},{"localized_name":"类型","name":"type","type":"COMBO","widget":{"name":"type"},"link":null},{"localized_name":"设备","name":"device","shape":7,"type":"COMBO","widget":{"name":"device"},"link":null}],"outputs":[{"label":"CLIP","localized_name":"CLIP","name":"CLIP","type":"CLIP","links":[]}],"properties":{"cnr_id":"comfy-core","ver":"0.8.2","Node name for S&R":"DualCLIPLoader","ue_properties":{"widget_ue_connectable":{},"version":"7.5.2","input_ue_unconnectable":{}}},"widgets_values":["gemma_3_12B_it_fp8_e4m3fn.safetensors","ltx-2-19b-embeddings_connector_distill_bf16.safetensors","ltxv","default"],"color":"#1f1f48","bgcolor":"rgba(24,24,27,.9)"},{"id":71,"type":"GetNode","pos":[929.392464413492,4277.280878689797],"size":[210,60],"flags":{"collapsed":true},"order":6,"mode":0,"inputs":[],"outputs":[{"name":"INT","type":"INT","links":[86]}],"properties":{"ue_properties":{"widget_ue_connectable":{},"version":"7.5.2","input_ue_unconnectable":{}}},"widgets_values":["width"],"color":"#1b4669","bgcolor":"#29699c"},{"id":51,"type":"GetNode","pos":[1417.7677927214052,3703.3855866275335],"size":[210,60],"flags":{"collapsed":true},"order":7,"mode":0,"inputs":[],"outputs":[{"name":"MODEL","type":"MODEL","links":[105]}],"properties":{"ue_properties":{"widget_ue_connectable":{},"version":"7.5.2","input_ue_unconnectable":{}}},"widgets_values":["model"],"color":"#1f1f48","bgcolor":"rgba(24,24,27,.9)"},{"id":67,"type":"MarkdownNote","pos":[60.03549352565943,4639.298553517395],"size":[291.99631835798823,102.45137621179947],"flags":{"collapsed":false},"order":8,"mode":0,"inputs":[],"outputs":[],"title":"Video settings","properties":{"ue_properties":{"widget_ue_connectable":{},"version":"7.5.2","input_ue_unconnectable":{}}},"widgets_values":["If low on Ram/Vram, try width height to 832 x 480 or 960 x 544.  If you can, run at 1280 x 720 or higher.\n\n\nLength in seconds :  try 5, 10 or 20. \nfps : 24 or 25 (or 48 or 50 if your pc can run it)"],"color":"#222","bgcolor":"#000"},{"id":79,"type":"MarkdownNote","pos":[-46.92258672529903,3753.1246865836433],"size":[382.280702747692,140],"flags":{"collapsed":false},"order":9,"mode":0,"inputs":[],"outputs":[],"title":"About Size","properties":{"ue_properties":{"widget_ue_connectable":{},"version":"7.5.2","input_ue_unconnectable":{}}},"widgets_values":["Width & height settings must be divisible by 32 + 1. \nFrame count must be divisible by 8 + 1. \n\n\nRunning with invalid parameters **will not cause errors**. Instead, the flow will silently choose the closest valid parameters. \n\nBy default, we are using 720p resolution. You can try 1920*1088 if you have a powerful GPU."],"color":"#222","bgcolor":"#000"},{"id":80,"type":"MarkdownNote","pos":[-46.92258672529903,3615.417010395611],"size":[382.280702747692,89.8245395507779],"flags":{"collapsed":false},"order":10,"mode":0,"inputs":[],"outputs":[],"title":"About  Models","properties":{"ue_properties":{"widget_ue_connectable":{},"version":"7.5.2","input_ue_unconnectable":{}}},"widgets_values":["Download models from here:\n\n\nhttps://huggingface.co/Kijai/LTXV2_comfy\n\nhttps://huggingface.co/unsloth/gemma-3-12b-it-GGUF/\n"],"color":"#222","bgcolor":"#000"},{"id":87,"type":"GetNode","pos":[2921.1879682194112,3709.772337557087],"size":[210,60],"flags":{"collapsed":true},"order":11,"mode":0,"inputs":[],"outputs":[{"name":"FLOAT","type":"FLOAT","links":[110]}],"properties":{"ue_properties":{"widget_ue_connectable":{},"version":"7.5.2","input_ue_unconnectable":{}}},"widgets_values":["fps"],"color":"#346434","bgcolor":"rgba(24,24,27,.9)"},{"id":88,"type":"GetNode","pos":[1740.5622917924213,4139.187984290914],"size":[275.56750142828105,60],"flags":{"collapsed":true},"order":12,"mode":0,"inputs":[],"outputs":[{"name":"BOOLEAN","type":"BOOLEAN","links":[115]}],"properties":{"ue_properties":{"widget_ue_connectable":{},"version":"7.5.2","input_ue_unconnectable":{}}},"widgets_values":["t2v_mode"]},{"id":90,"type":"VRAM_Debug","pos":[2143.15569652738,3750.4826236507224],"size":[304.376953125,186],"flags":{"collapsed":true},"order":65,"mode":0,"inputs":[{"localized_name":"any_input","name":"any_input","shape":7,"type":"*","link":118},{"localized_name":"image_pass","name":"image_pass","shape":7,"type":"IMAGE","link":null},{"localized_name":"model_pass","name":"model_pass","shape":7,"type":"MODEL","link":null},{"localized_name":"empty_cache","name":"empty_cache","type":"BOOLEAN","widget":{"name":"empty_cache"},"link":null},{"localized_name":"gc_collect","name":"gc_collect","type":"BOOLEAN","widget":{"name":"gc_collect"},"link":null},{"localized_name":"unload_all_models","name":"unload_all_models","type":"BOOLEAN","widget":{"name":"unload_all_models"},"link":null}],"outputs":[{"localized_name":"any_output","name":"any_output","type":"*","links":[119]},{"localized_name":"image_pass","name":"image_pass","type":"IMAGE","links":null},{"localized_name":"model_pass","name":"model_pass","type":"MODEL","links":null},{"label":"前剩余内存","localized_name":"freemem_before","name":"freemem_before","type":"INT","links":null},{"label":"后剩余内存","localized_name":"freemem_after","name":"freemem_after","type":"INT","links":null}],"properties":{"cnr_id":"comfyui-kjnodes","ver":"f710f2635dbadbaf1ccf7d25572daa7dfec80bfd","Node name for S&R":"VRAM_Debug","ue_properties":{"widget_ue_connectable":{},"version":"7.5.2","input_ue_unconnectable":{}}},"widgets_values":[true,true,false]},{"id":81,"type":"MarkdownNote","pos":[-46.92258672529903,3958.323519389528],"size":[382.280702747692,140],"flags":{"collapsed":false},"order":13,"mode":0,"inputs":[],"outputs":[],"title":"Prompting LTX-2","properties":{"ue_properties":{"widget_ue_connectable":{},"version":"7.5.2","input_ue_unconnectable":{}}},"widgets_values":["## LTX-2 Prompting Tips\n1. **Core Actions**: Describe events and actions as they occur over time  \n2. **Audio**: Describe sounds and dialogue needed for the scene  \n3. **Reference Image**: Do not repeat details already present  \n4. **Consistency**: Avoid instructions that do not match the reference image, as this will degrade results"],"color":"#222","bgcolor":"#000"},{"id":61,"type":"INTConstant","pos":[413.8468634949593,4685.456365963766],"size":[210,58],"flags":{"collapsed":false},"order":14,"mode":0,"inputs":[{"localized_name":"value","name":"value","type":"INT","widget":{"name":"value"},"link":null}],"outputs":[{"label":"值","localized_name":"value","name":"value","type":"INT","links":[79]}],"properties":{"cnr_id":"comfyui-kjnodes","ver":"c6ce76d00bb8177d1b0286cad891df08eff5226e","Node name for S&R":"INTConstant","ue_properties":{"widget_ue_connectable":{},"version":"7.5.2","input_ue_unconnectable":{}}},"widgets_values":[1280],"color":"#006691","bgcolor":"rgba(24,24,27,.9)"},{"id":62,"type":"INTConstant","pos":[650.0692705690285,4686.823575348423],"size":[210,58],"flags":{"collapsed":false},"order":15,"mode":0,"inputs":[{"localized_name":"value","name":"value","type":"INT","widget":{"name":"value"},"link":null}],"outputs":[{"label":"值","localized_name":"value","name":"value","type":"INT","links":[78]}],"properties":{"cnr_id":"comfyui-kjnodes","ver":"c6ce76d00bb8177d1b0286cad891df08eff5226e","Node name for S&R":"INTConstant","ue_properties":{"widget_ue_connectable":{},"version":"7.5.2","input_ue_unconnectable":{}}},"widgets_values":[704],"color":"#006691","bgcolor":"rgba(24,24,27,.9)"},{"id":42,"type":"UNETLoader","pos":[87.47278399260715,4385.830815833363],"size":[320.66467204536764,89.41528260002815],"flags":{"collapsed":true},"order":16,"mode":0,"inputs":[{"localized_name":"UNet名称","name":"unet_name","type":"COMBO","widget":{"name":"unet_name"},"link":null},{"localized_name":"数据类型","name":"weight_dtype","type":"COMBO","widget":{"name":"weight_dtype"},"link":null}],"outputs":[{"label":"模型","localized_name":"模型","name":"MODEL","type":"MODEL","links":[]}],"properties":{"cnr_id":"comfy-core","ver":"0.8.2","Node name for S&R":"UNETLoader","ue_properties":{"widget_ue_connectable":{},"version":"7.5.2","input_ue_unconnectable":{}}},"widgets_values":["ltx-2-19b-distilled-fp8_transformer_only.safetensors","default"],"color":"#1f1f48","bgcolor":"rgba(24,24,27,.9)"},{"id":37,"type":"SetNode","pos":[544.5809747394173,4185.866171747739],"size":[210,34],"flags":{"collapsed":true},"order":45,"mode":0,"inputs":[{"name":"CLIP","type":"CLIP","link":62}],"outputs":[{"label":"输出","name":"*","type":"*","links":null}],"title":"Set_CLIP","properties":{"previousName":"","ue_properties":{"widget_ue_connectable":{},"version":"7.5.2","input_ue_unconnectable":{}}},"widgets_values":["clip"],"color":"#432","bgcolor":"#653"},{"id":7,"type":"LTXVConcatAVLatent","pos":[1740.5622917924213,4248.1998417927525],"size":[275.56750142828105,60],"flags":{},"order":64,"mode":0,"inputs":[{"label":"video_latent","localized_name":"video_latent","name":"video_latent","type":"LATENT","link":114},{"label":"audio_latent","localized_name":"audio_latent","name":"audio_latent","type":"LATENT","link":15}],"outputs":[{"label":"latent","localized_name":"latent","name":"latent","type":"LATENT","links":[118]}],"properties":{"cnr_id":"comfy-core","ver":"0.7.0","Node name for S&R":"LTXVConcatAVLatent","ue_properties":{"widget_ue_connectable":{},"version":"7.5.2","input_ue_unconnectable":{}},"enableTabs":false,"tabWidth":65,"tabXOffset":10,"hasSecondTab":false,"secondTabText":"Send Back","secondTabOffset":80,"secondTabWidth":65},"widgets_values":[]},{"id":84,"type":"LTXVChunkFeedForward","pos":[446.5674616975186,3991.240248041415],"size":[295.5602600077674,82],"flags":{},"order":55,"mode":4,"inputs":[{"label":"model","localized_name":"model","name":"model","type":"MODEL","link":108},{"label":"chunks","localized_name":"chunks","name":"chunks","type":"INT","widget":{"name":"chunks"},"link":null},{"label":"dim_threshold","localized_name":"dim_threshold","name":"dim_threshold","type":"INT","widget":{"name":"dim_threshold"},"link":null}],"outputs":[{"label":"model","localized_name":"model","name":"model","type":"MODEL","links":[109]}],"properties":{"cnr_id":"comfyui-kjnodes","ver":"4cb4ede5c3a4cebc14bb63b49b62f03cd16d44a5","Node name for S&R":"LTXVChunkFeedForward","ue_properties":{"widget_ue_connectable":{},"version":"7.5.2","input_ue_unconnectable":{}}},"widgets_values":[2,4096]},{"id":54,"type":"GetNode","pos":[1740.5622917924213,3724.111648400179],"size":[275.56750142828105,60],"flags":{"collapsed":true},"order":17,"mode":0,"inputs":[],"outputs":[{"name":"VAE","type":"VAE","links":[72]}],"properties":{"ue_properties":{"widget_ue_connectable":{},"version":"7.5.2","input_ue_unconnectable":{}}},"widgets_values":["vae_audio"],"color":"#af3535","bgcolor":"rgba(24,24,27,.9)"},{"id":76,"type":"GetNode","pos":[1740.5622917924213,3917.6579575010683],"size":[275.56750142828105,60],"flags":{"collapsed":true},"order":18,"mode":0,"inputs":[],"outputs":[{"name":"INT","type":"INT","links":[94,95]}],"properties":{"ue_properties":{"widget_ue_connectable":{},"version":"7.5.2","input_ue_unconnectable":{}}},"widgets_values":["frames"],"color":"#1b4669","bgcolor":"#29699c"},{"id":94,"type":"SetNode","pos":[1425.8761393492478,4508.731523529796],"size":[210,60],"flags":{"collapsed":true},"order":61,"mode":0,"inputs":[{"name":"CONDITIONING","type":"CONDITIONING","link":122}],"outputs":[{"label":"输出","name":"*","type":"*","links":null}],"title":"Set_CONDITIONING","properties":{"previousName":"positive","ue_properties":{"widget_ue_connectable":{},"version":"7.5.2","input_ue_unconnectable":{}}},"widgets_values":["positive"],"color":"#332922","bgcolor":"#593930"},{"id":95,"type":"SetNode","pos":[1397.6085546849015,4534.511690474841],"size":[210,58],"flags":{"collapsed":true},"order":62,"mode":0,"inputs":[{"name":"CONDITIONING","type":"CONDITIONING","link":123}],"outputs":[{"label":"输出","name":"*","type":"*","links":null}],"title":"Set_CONDITIONING","properties":{"previousName":"negative","ue_properties":{"widget_ue_connectable":{},"version":"7.5.2","input_ue_unconnectable":{}}},"widgets_values":["negative"],"color":"#332922","bgcolor":"#593930"},{"id":96,"type":"GetNode","pos":[2170.37686864892,3735.603746691242],"size":[210,60],"flags":{"collapsed":true},"order":19,"mode":0,"inputs":[],"outputs":[{"name":"CONDITIONING","type":"CONDITIONING","links":[129]}],"properties":{"ue_properties":{"widget_ue_connectable":{},"version":"7.5.2","input_ue_unconnectable":{}}},"widgets_values":["positive"],"color":"#38291f","bgcolor":"rgba(24,24,27,.9)"},{"id":97,"type":"GetNode","pos":[2142.203010500673,3750.9705773625697],"size":[210,58],"flags":{"collapsed":true},"order":20,"mode":0,"inputs":[],"outputs":[{"name":"CONDITIONING","type":"CONDITIONING","links":[128]}],"properties":{"ue_properties":{"widget_ue_connectable":{},"version":"7.5.2","input_ue_unconnectable":{}}},"widgets_values":["negative"],"color":"#38291f","bgcolor":"rgba(24,24,27,.9)"},{"id":99,"type":"SetNode","pos":[961.9131760381415,4399.564636670981],"size":[210,58],"flags":{"collapsed":true},"order":60,"mode":0,"inputs":[{"name":"INT","type":"INT","link":131}],"outputs":[{"label":"输出","name":"*","type":"*","links":null}],"title":"Set_INT","properties":{"previousName":"height_firstframe","ue_properties":{"widget_ue_connectable":{},"version":"7.5.2","input_ue_unconnectable":{}}},"widgets_values":["height_firstframe"],"color":"#1b4669","bgcolor":"#29699c"},{"id":98,"type":"SetNode","pos":[959.4219490606026,4335.608470643142],"size":[210,60],"flags":{"collapsed":true},"order":59,"mode":0,"inputs":[{"name":"INT","type":"INT","link":130}],"outputs":[{"label":"输出","name":"*","type":"*","links":null}],"title":"Set_INT","properties":{"previousName":"width_firstframe","ue_properties":{"widget_ue_connectable":{},"version":"7.5.2","input_ue_unconnectable":{}}},"widgets_values":["width_firstframe"],"color":"#1b4669","bgcolor":"#29699c"},{"id":101,"type":"GetNode","pos":[1740.5622917924213,3906.346716599933],"size":[275.56750142828105,58],"flags":{"collapsed":true},"order":21,"mode":0,"inputs":[],"outputs":[{"name":"INT","type":"INT","links":[133]}],"properties":{"ue_properties":{"widget_ue_connectable":{},"version":"7.5.2","input_ue_unconnectable":{}}},"widgets_values":["height_firstframe"],"color":"#1b4669","bgcolor":"#29699c"},{"id":100,"type":"GetNode","pos":[1740.5622917924213,3943.539717432236],"size":[275.56750142828105,60],"flags":{"collapsed":true},"order":22,"mode":0,"inputs":[],"outputs":[{"name":"INT","type":"INT","links":[132]}],"properties":{"ue_properties":{"widget_ue_connectable":{},"version":"7.5.2","input_ue_unconnectable":{}}},"widgets_values":["width_firstframe"],"color":"#1b4669","bgcolor":"#29699c"},{"id":5,"type":"EmptyLTXVLatentVideo","pos":[1740.5622917924213,3853.4272488144857],"size":[275.56750142828105,146.66666666666669],"flags":{"collapsed":false},"order":44,"mode":0,"inputs":[{"label":"width","localized_name":"宽度","name":"width","type":"INT","widget":{"name":"width"},"link":132},{"label":"height","localized_name":"高度","name":"height","type":"INT","widget":{"name":"height"},"link":133},{"label":"length","localized_name":"长度","name":"length","type":"INT","widget":{"name":"length"},"link":94},{"label":"batch_size","localized_name":"批量大小","name":"batch_size","type":"INT","widget":{"name":"batch_size"},"link":null}],"outputs":[{"label":"LATENT","localized_name":"Latent","name":"LATENT","type":"LATENT","links":[112]}],"properties":{"cnr_id":"comfy-core","ver":"0.3.60","Node name for S&R":"EmptyLTXVLatentVideo","ue_properties":{"widget_ue_connectable":{},"version":"7.5.2","input_ue_unconnectable":{}},"enableTabs":false,"tabWidth":65,"tabXOffset":10,"hasSecondTab":false,"secondTabText":"Send Back","secondTabOffset":80,"secondTabWidth":65},"widgets_values":[768,512,97,1]},{"id":73,"type":"GetNode","pos":[1385.9262618403916,4520.638679360738],"size":[210,60],"flags":{"collapsed":true},"order":23,"mode":0,"inputs":[],"outputs":[{"name":"FLOAT","type":"FLOAT","links":[91]}],"properties":{"ue_properties":{"widget_ue_connectable":{},"version":"7.5.2","input_ue_unconnectable":{}}},"widgets_values":["fps"],"color":"#346434","bgcolor":"rgba(24,24,27,.9)"},{"id":10,"type":"LTXVConditioning","pos":[1340.9929565647026,4474.509964123478],"size":[269.0482962497696,78],"flags":{},"order":54,"mode":0,"inputs":[{"label":"positive","localized_name":"正面条件","name":"positive","type":"CONDITIONING","link":17},{"label":"negative","localized_name":"负面条件","name":"negative","type":"CONDITIONING","link":18},{"label":"frame_rate","localized_name":"帧率","name":"frame_rate","type":"FLOAT","widget":{"name":"frame_rate"},"link":91}],"outputs":[{"label":"positive","localized_name":"正面条件","name":"positive","type":"CONDITIONING","links":[122]},{"label":"negative","localized_name":"负面条件","name":"negative","type":"CONDITIONING","links":[123]}],"properties":{"cnr_id":"comfy-core","ver":"0.3.56","Node name for S&R":"LTXVConditioning","ue_properties":{"widget_ue_connectable":{},"version":"7.5.2","input_ue_unconnectable":{}},"enableTabs":false,"tabWidth":65,"tabXOffset":10,"hasSecondTab":false,"secondTabText":"Send Back","secondTabOffset":80,"secondTabWidth":65},"widgets_values":[25]},{"id":38,"type":"SetNode","pos":[453.7946545018989,4362.063170527353],"size":[210,34],"flags":{"collapsed":true},"order":46,"mode":0,"inputs":[{"name":"VAE","type":"VAE","link":63}],"outputs":[{"label":"输出","name":"*","type":"*","links":null}],"title":"Set_VAE","properties":{"previousName":"","ue_properties":{"widget_ue_connectable":{},"version":"7.5.2","input_ue_unconnectable":{}}},"widgets_values":["vae_audio"],"color":"#322","bgcolor":"#533"},{"id":17,"type":"PrimitiveInt","pos":[2081.258237496355,4259.589206748771],"size":[278.7807055786143,82],"flags":{},"order":24,"mode":0,"inputs":[{"label":"value","localized_name":"数值","name":"value","type":"INT","widget":{"name":"value"},"link":null}],"outputs":[{"label":"INT","localized_name":"整数","name":"INT","type":"INT","links":[49]}],"title":"SEED","properties":{"cnr_id":"comfy-core","ver":"0.10.0","Node name for S&R":"PrimitiveInt","ue_properties":{"widget_ue_connectable":{},"input_ue_unconnectable":{},"version":"7.5.2"}},"widgets_values":[55,"fixed"],"color":"#006691","bgcolor":"rgba(24,24,27,.9)"},{"id":46,"type":"LoraLoaderModelOnly","pos":[428.5038853368079,3812.3138164487073],"size":[332.4827641267634,82],"flags":{},"order":48,"mode":0,"inputs":[{"label":"模型","localized_name":"模型","name":"model","type":"MODEL","link":66},{"localized_name":"LoRA名称","name":"lora_name","type":"COMBO","widget":{"name":"lora_name"},"link":null},{"localized_name":"模型强度","name":"strength_model","type":"FLOAT","widget":{"name":"strength_model"},"link":null}],"outputs":[{"label":"模型","localized_name":"模型","name":"MODEL","type":"MODEL","links":[108]}],"properties":{"cnr_id":"comfy-core","ver":"0.3.75","Node name for S&R":"LoraLoaderModelOnly","enableTabs":false,"tabWidth":65,"tabXOffset":10,"hasSecondTab":false,"secondTabText":"Send Back","secondTabOffset":80,"secondTabWidth":65,"models":[{"name":"ltx-2-19b-distilled-lora-384.safetensors","url":"https://huggingface.co/Lightricks/LTX-2/resolve/main/ltx-2-19b-distilled-lora-384.safetensors","directory":"loras"}],"ue_properties":{"widget_ue_connectable":{},"version":"7.5.2","input_ue_unconnectable":{}}},"widgets_values":["ltx-2-19b-distilled-lora_resized_dynamic_fro09_avg_rank_175_bf16.safetensors",0.6],"color":"#1f1f48","bgcolor":"rgba(24,24,27,.9)"},{"id":41,"type":"DualCLIPLoaderGGUF","pos":[428.91426089071354,4144.927660142174],"size":[332.4827641267634,111.14057719239372],"flags":{},"order":25,"mode":0,"inputs":[{"label":"clip_name1","localized_name":"clip_name1","name":"clip_name1","type":"COMBO","widget":{"name":"clip_name1"},"link":null},{"label":"clip_name2","localized_name":"clip_name2","name":"clip_name2","type":"COMBO","widget":{"name":"clip_name2"},"link":null},{"label":"type","localized_name":"type","name":"type","type":"COMBO","widget":{"name":"type"},"link":null}],"outputs":[{"label":"CLIP","localized_name":"CLIP","name":"CLIP","type":"CLIP","links":[62]}],"title":"CLIP ( Gemma GGUF +  LTX embedding)","properties":{"cnr_id":"ComfyUI-GGUF","ver":"6ea2651e7df66d7585f6ffee804b20e92fb38b8a","Node name for S&R":"DualCLIPLoaderGGUF","ue_properties":{"widget_ue_connectable":{},"version":"7.5.2","input_ue_unconnectable":{}}},"widgets_values":["gemma3-12b-it-q2_k.gguf","ltx-2-19b-embeddings_connector_distill_bf16.safetensors","ltxv"],"color":"#1f1f48","bgcolor":"rgba(24,24,27,.9)"},{"id":50,"type":"VAELoaderKJ","pos":[428.05749802531517,4303.9735228171],"size":[332.4827641267634,108.00311157930264],"flags":{},"order":26,"mode":0,"inputs":[{"label":"vae_name","localized_name":"vae_name","name":"vae_name","type":"COMBO","widget":{"name":"vae_name"},"link":null},{"label":"device","localized_name":"device","name":"device","type":"COMBO","widget":{"name":"device"},"link":null},{"label":"weight_dtype","localized_name":"weight_dtype","name":"weight_dtype","type":"COMBO","widget":{"name":"weight_dtype"},"link":null}],"outputs":[{"label":"VAE","localized_name":"VAE","name":"VAE","type":"VAE","links":[63]}],"title":"VAELoader KJ  (audio vae)","properties":{"cnr_id":"comfyui-kjnodes","ver":"487c7d86a0230aae3d8c0a37d517159b73834f85","Node name for S&R":"VAELoaderKJ","ue_properties":{"widget_ue_connectable":{},"version":"7.5.2","input_ue_unconnectable":{}}},"widgets_values":["LTX2_audio_vae_bf16.safetensors","main_device","bf16"],"color":"#1f1f48","bgcolor":"rgba(24,24,27,.9)"},{"id":49,"type":"VAELoader","pos":[429.9509439578463,4463.476611960006],"size":[332.4827641267634,61.42705146159551],"flags":{},"order":27,"mode":0,"inputs":[{"localized_name":"vae名称","name":"vae_name","type":"COMBO","widget":{"name":"vae_name"},"link":null}],"outputs":[{"localized_name":"VAE","name":"VAE","type":"VAE","links":[67]}],"properties":{"cnr_id":"comfy-core","ver":"0.8.2","Node name for S&R":"VAELoader","ue_properties":{"widget_ue_connectable":{},"version":"7.5.2","input_ue_unconnectable":{}}},"widgets_values":["LTX2_video_vae_bf16.safetensors"],"color":"#1f1f48","bgcolor":"rgba(24,24,27,.9)"},{"id":47,"type":"UnetLoaderGGUF","pos":[425.3172186596748,3683.354306131676],"size":[332.4827641267634,84.88806513948657],"flags":{"collapsed":false},"order":28,"mode":0,"inputs":[{"label":"unet_name","localized_name":"unet_name","name":"unet_name","type":"COMBO","widget":{"name":"unet_name"},"link":null}],"outputs":[{"label":"MODEL","localized_name":"模型","name":"MODEL","type":"MODEL","links":[66]}],"properties":{"cnr_id":"ComfyUI-GGUF","ver":"6ea2651e7df66d7585f6ffee804b20e92fb38b8a","Node name for S&R":"UnetLoaderGGUF","ue_properties":{"widget_ue_connectable":{},"version":"7.5.2","input_ue_unconnectable":{}}},"widgets_values":["ltx-2-19b-dev_Q8_0.gguf"],"color":"#1f1f48","bgcolor":"rgba(24,24,27,.9)"},{"id":55,"type":"GetNode","pos":[1740.5622917924213,4149.5413494754985],"size":[275.56750142828105,60],"flags":{"collapsed":true},"order":29,"mode":0,"inputs":[],"outputs":[{"name":"VAE","type":"VAE","links":[113]}],"properties":{"ue_properties":{"widget_ue_connectable":{},"version":"7.5.2","input_ue_unconnectable":{}}},"widgets_values":["vae"],"color":"#af3535","bgcolor":"rgba(24,24,27,.9)"},{"id":85,"type":"LTXVImgToVideoInplace","pos":[1740.5622917924213,4058.6559455730535],"size":[275.56750142828105,122],"flags":{},"order":57,"mode":0,"inputs":[{"label":"vae","localized_name":"vae","name":"vae","type":"VAE","link":113},{"label":"image","localized_name":"图像","name":"image","type":"IMAGE","link":111},{"label":"latent","localized_name":"潜空间","name":"latent","type":"LATENT","link":112},{"label":"strength","localized_name":"强度","name":"strength","type":"FLOAT","widget":{"name":"strength"},"link":null},{"label":"bypass","localized_name":"跳过","name":"bypass","type":"BOOLEAN","widget":{"name":"bypass"},"link":115}],"outputs":[{"label":"latent","localized_name":"潜空间","name":"latent","type":"LATENT","links":[114]}],"properties":{"cnr_id":"comfy-core","ver":"0.7.0","Node name for S&R":"LTXVImgToVideoInplace","ue_properties":{"widget_ue_connectable":{"bypass":true},"version":"7.5.2","input_ue_unconnectable":{}}},"widgets_values":[1,false]},{"id":6,"type":"LTXVEmptyLatentAudio","pos":[1740.5622917924213,3683.4294773251236],"size":[275.56750142828105,120],"flags":{},"order":53,"mode":0,"inputs":[{"label":"audio_vae","localized_name":"音频VAE","name":"audio_vae","type":"VAE","link":72},{"label":"frames_number","localized_name":"帧数","name":"frames_number","type":"INT","widget":{"name":"frames_number"},"link":95},{"label":"frame_rate","localized_name":"帧率","name":"frame_rate","type":"INT","widget":{"name":"frame_rate"},"link":93},{"label":"batch_size","localized_name":"批量大小","name":"batch_size","type":"INT","widget":{"name":"batch_size"},"link":null}],"outputs":[{"label":"Latent","localized_name":"潜空间","name":"Latent","type":"LATENT","links":[15]}],"properties":{"cnr_id":"comfy-core","ver":"0.3.68","Node name for S&R":"LTXVEmptyLatentAudio","ue_properties":{"widget_ue_connectable":{},"version":"7.5.2","input_ue_unconnectable":{}},"enableTabs":false,"tabWidth":65,"tabXOffset":10,"hasSecondTab":false,"secondTabText":"Send Back","secondTabOffset":80,"secondTabWidth":65},"widgets_values":[97,25,1]},{"id":103,"type":"SetNode","pos":[967.920249677103,4279.32569222874],"size":[210,60],"flags":{"collapsed":true},"order":58,"mode":0,"inputs":[{"name":"IMAGE","type":"IMAGE","link":134}],"outputs":[{"label":"输出","name":"*","type":"*","links":null}],"title":"Set_IMAGE","properties":{"previousName":"ref_image","ue_properties":{"widget_ue_connectable":{},"version":"7.5.2","input_ue_unconnectable":{}}},"widgets_values":["ref_image"],"color":"#2a363b","bgcolor":"#3f5159"},{"id":92,"type":"MarkdownNote","pos":[-46.92258672529903,4155.175179719436],"size":[382.280702747692,93.01754604492271],"flags":{"collapsed":false},"order":30,"mode":0,"inputs":[],"outputs":[],"title":"IMPORTANT LORA!","properties":{"ue_properties":{"widget_ue_connectable":{},"version":"7.5.2","input_ue_unconnectable":{}}},"widgets_values":["For this K-Sampler workflow to work, you must use the Image-2-Video adapter lora from here :\n\nhttps://huggingface.co/MachineDelusions/LTX-2_Image2Video_Adapter_LoRa"],"color":"#008181","bgcolor":"rgba(24,24,27,.9)"},{"id":78,"type":"Power Lora Loader (rgthree)","pos":[1294.916486713186,3663.3636029444233],"size":[367.49300405009456,166],"flags":{},"order":41,"mode":0,"inputs":[{"dir":3,"label":"模型","name":"model","type":"MODEL","link":105},{"dir":3,"label":"CLIP","name":"clip","type":"CLIP","link":null}],"outputs":[{"dir":4,"label":"模型","name":"MODEL","shape":3,"type":"MODEL","links":[101]},{"dir":4,"label":"CLIP","name":"CLIP","shape":3,"type":"CLIP","links":null}],"properties":{"cnr_id":"rgthree-comfy","ver":"8ff50e4521881eca1fe26aec9615fc9362474931","Show Strengths":"Single Strength","ue_properties":{"widget_ue_connectable":{},"version":"7.5.2","input_ue_unconnectable":{}}},"widgets_values":[{},{"type":"PowerLoraLoaderHeaderWidget"},{"on":true,"lora":"LTX\\LTX-2\\LTX-2-Image2Vid-Adapter.safetensors","strength":0.5,"strengthTwo":null},{"on":false,"lora":"LTX\\v2\\ltx-2-19b-ic-lora-detailer.safetensors","strength":0.6,"strengthTwo":null},{},""],"color":"#008181","bgcolor":"rgba(24,24,27,.9)"},{"id":27,"type":"KSampler","pos":[2083.4287024767373,3683.8779242057485],"size":[284.12338860724776,511.0975786639874],"flags":{},"order":66,"mode":0,"inputs":[{"label":"模型","localized_name":"模型","name":"model","type":"MODEL","link":101},{"label":"正面条件","localized_name":"正面条件","name":"positive","type":"CONDITIONING","link":129},{"label":"负面条件","localized_name":"负面条件","name":"negative","type":"CONDITIONING","link":128},{"label":"Latent","localized_name":"Latent图像","name":"latent_image","type":"LATENT","link":119},{"localized_name":"种子","name":"seed","type":"INT","widget":{"name":"seed"},"link":49},{"localized_name":"步数","name":"steps","type":"INT","widget":{"name":"steps"},"link":null},{"localized_name":"cfg","name":"cfg","type":"FLOAT","widget":{"name":"cfg"},"link":null},{"localized_name":"采样器名称","name":"sampler_name","type":"COMBO","widget":{"name":"sampler_name"},"link":null},{"localized_name":"调度器","name":"scheduler","type":"COMBO","widget":{"name":"scheduler"},"link":null},{"localized_name":"降噪","name":"denoise","type":"FLOAT","widget":{"name":"denoise"},"link":null}],"outputs":[{"label":"Latent","localized_name":"Latent","name":"LATENT","type":"LATENT","links":[2]}],"properties":{"cnr_id":"comfy-core","ver":"0.7.0","Node name for S&R":"KSampler","ue_properties":{"widget_ue_connectable":{},"input_ue_unconnectable":{},"version":"7.5.2"}},"widgets_values":[937,"fixed",8,1,"lcm","simple",1]},{"id":66,"type":"INTConstant","pos":[893.1903930564415,4686.306204314231],"size":[210,58],"flags":{},"order":31,"mode":0,"inputs":[{"localized_name":"value","name":"value","type":"INT","widget":{"name":"value"},"link":null}],"outputs":[{"label":"值","localized_name":"value","name":"value","type":"INT","links":[82]}],"properties":{"cnr_id":"comfyui-kjnodes","ver":"c6ce76d00bb8177d1b0286cad891df08eff5226e","Node name for S&R":"INTConstant","ue_properties":{"widget_ue_connectable":{},"version":"7.5.2","input_ue_unconnectable":{}}},"widgets_values":[5],"color":"#006691","bgcolor":"rgba(24,24,27,.9)"},{"id":2,"type":"LTXVSeparateAVLatent","pos":[2432.103349744379,3673.6861256600314],"size":[234.124545778805,46],"flags":{},"order":67,"mode":0,"inputs":[{"label":"av_latent","localized_name":"音视频潜空间","name":"av_latent","type":"LATENT","link":2}],"outputs":[{"label":"video_latent","localized_name":"video_latent","name":"video_latent","type":"LATENT","links":[121]},{"label":"audio_latent","localized_name":"audio_latent","name":"audio_latent","type":"LATENT","links":[56]}],"properties":{"cnr_id":"comfy-core","ver":"0.5.1","Node name for S&R":"LTXVSeparateAVLatent","ue_properties":{"widget_ue_connectable":{},"version":"7.5.2","input_ue_unconnectable":{}},"enableTabs":false,"tabWidth":65,"tabXOffset":10,"hasSecondTab":false,"secondTabText":"Send Back","secondTabOffset":80,"secondTabWidth":65},"widgets_values":[]},{"id":56,"type":"GetNode","pos":[2496.377699906609,4013.058534480133],"size":[234.124545778805,60],"flags":{"collapsed":true},"order":32,"mode":0,"inputs":[],"outputs":[{"name":"VAE","type":"VAE","links":[77]}],"properties":{"ue_properties":{"widget_ue_connectable":{},"version":"7.5.2","input_ue_unconnectable":{}}},"widgets_values":["vae_audio"],"color":"#af3535","bgcolor":"rgba(24,24,27,.9)"},{"id":34,"type":"LTXVAudioVAEDecode","pos":[2432.1033497443805,3984.057334877933],"size":[234.124545778805,46],"flags":{},"order":69,"mode":0,"inputs":[{"label":"samples","localized_name":"样本","name":"samples","type":"LATENT","link":56},{"label":"audio_vae","localized_name":"音频VAE","name":"audio_vae","type":"VAE","link":77}],"outputs":[{"label":"Audio","localized_name":"音频","name":"Audio","type":"AUDIO","links":[38]}],"properties":{"cnr_id":"comfy-core","ver":"0.7.0","Node name for S&R":"LTXVAudioVAEDecode","ue_properties":{"widget_ue_connectable":{},"version":"7.5.2","input_ue_unconnectable":{}},"enableTabs":false,"tabWidth":65,"tabXOffset":10,"hasSecondTab":false,"secondTabText":"Send Back","secondTabOffset":80,"secondTabWidth":65},"widgets_values":[]},{"id":104,"type":"GetNode","pos":[2371.098061608397,3301.7354648411288],"size":[210,60],"flags":{"collapsed":true},"order":33,"mode":0,"inputs":[],"outputs":[{"name":"IMAGE","type":"IMAGE","links":[135]}],"properties":{"ue_properties":{"widget_ue_connectable":{},"version":"7.5.2","input_ue_unconnectable":{}}},"widgets_values":["ref_image"],"color":"#006691","bgcolor":"rgba(24,24,27,.9)"},{"id":102,"type":"ColorMatch","pos":[2622.216679291509,3251.423255775317],"size":[270,126],"flags":{"collapsed":false},"order":50,"mode":4,"inputs":[{"label":"参考图像","localized_name":"image_ref","name":"image_ref","type":"IMAGE","link":135},{"label":"目标图像","localized_name":"image_target","name":"image_target","type":"IMAGE","link":null},{"localized_name":"method","name":"method","type":"COMBO","widget":{"name":"method"},"link":null},{"localized_name":"strength","name":"strength","shape":7,"type":"FLOAT","widget":{"name":"strength"},"link":null},{"localized_name":"multithread","name":"multithread","shape":7,"type":"BOOLEAN","widget":{"name":"multithread"},"link":null}],"outputs":[{"label":"图像","localized_name":"image","name":"image","type":"IMAGE","links":[]}],"properties":{"cnr_id":"comfyui-kjnodes","ver":"f710f2635dbadbaf1ccf7d25572daa7dfec80bfd","Node name for S&R":"ColorMatch","ue_properties":{"widget_ue_connectable":{},"version":"7.5.2","input_ue_unconnectable":{}}},"widgets_values":["mkl",1,true]},{"id":3,"type":"VAEDecodeTiled","pos":[2428.682295622842,3771.76996309388],"size":[234.124545778805,151.37982516235388],"flags":{},"order":68,"mode":0,"inputs":[{"label":"Latent","localized_name":"Latent","name":"samples","type":"LATENT","link":121},{"label":"VAE","localized_name":"vae","name":"vae","type":"VAE","link":75},{"localized_name":"分块尺寸","name":"tile_size","type":"INT","widget":{"name":"tile_size"},"link":null},{"localized_name":"重叠","name":"overlap","type":"INT","widget":{"name":"overlap"},"link":null},{"localized_name":"时间尺寸","name":"temporal_size","type":"INT","widget":{"name":"temporal_size"},"link":null},{"localized_name":"时间重叠","name":"temporal_overlap","type":"INT","widget":{"name":"temporal_overlap"},"link":null}],"outputs":[{"label":"图像","localized_name":"图像","name":"IMAGE","type":"IMAGE","links":[140]}],"properties":{"cnr_id":"comfy-core","ver":"0.7.0","Node name for S&R":"VAEDecodeTiled","ue_properties":{"widget_ue_connectable":{},"version":"7.5.2","input_ue_unconnectable":{}},"enableTabs":false,"tabWidth":65,"tabXOffset":10,"hasSecondTab":false,"secondTabText":"Send Back","secondTabOffset":80,"secondTabWidth":65},"widgets_values":[512,64,4096,8]},{"id":24,"type":"VHS_VideoCombine","pos":[2729.10368524734,3622.3411326459754],"size":[394.4596534755383,334],"flags":{},"order":70,"mode":0,"inputs":[{"label":"图像","localized_name":"images","name":"images","type":"IMAGE","link":140},{"label":"音频","localized_name":"audio","name":"audio","shape":7,"type":"AUDIO","link":38},{"label":"批次管理","localized_name":"meta_batch","name":"meta_batch","shape":7,"type":"VHS_BatchManager","link":null},{"localized_name":"vae","name":"vae","shape":7,"type":"VAE","link":null},{"localized_name":"frame_rate","name":"frame_rate","type":"FLOAT","widget":{"name":"frame_rate"},"link":110},{"localized_name":"loop_count","name":"loop_count","type":"INT","widget":{"name":"loop_count"},"link":null},{"localized_name":"filename_prefix","name":"filename_prefix","type":"STRING","widget":{"name":"filename_prefix"},"link":null},{"localized_name":"format","name":"format","type":"COMBO","widget":{"name":"format"},"link":null},{"localized_name":"pingpong","name":"pingpong","type":"BOOLEAN","widget":{"name":"pingpong"},"link":null},{"localized_name":"save_output","name":"save_output","type":"BOOLEAN","widget":{"name":"save_output"},"link":null},{"name":"pix_fmt","type":["yuv420p","yuv420p10le"],"widget":{"name":"pix_fmt"},"link":null},{"name":"crf","type":"INT","widget":{"name":"crf"},"link":null},{"label":"保存元数据","localized_name":"保存元数据","name":"save_metadata","type":"BOOLEAN","widget":{"name":"save_metadata"},"link":null},{"name":"trim_to_audio","type":"BOOLEAN","widget":{"name":"trim_to_audio"},"link":null}],"outputs":[{"label":"文件名","localized_name":"Filenames","name":"Filenames","type":"VHS_FILENAMES","links":null}],"properties":{"cnr_id":"comfyui-videohelpersuite","ver":"3234937ff5f3ca19068aaba5042771514de2429d","Node name for S&R":"VHS_VideoCombine","ue_properties":{"widget_ue_connectable":{},"input_ue_unconnectable":{},"version":"7.5.2"}},"widgets_values":{"frame_rate":24,"loop_count":0,"filename_prefix":"LTX-2-Simple","format":"video/h264-mp4","pix_fmt":"yuv420p","crf":19,"save_metadata":true,"trim_to_audio":false,"pingpong":false,"save_output":true,"videopreview":{"hidden":false,"paused":false,"params":{"filename":"LTX-2-Simple_00041-audio.mp4","subfolder":"","type":"output","format":"video/h264-mp4","frame_rate":24,"workflow":"LTX-2-Simple_00041.png","fullpath":"E:\\AI\\ComfyUI\\output\\LTX-2-Simple_00041-audio.mp4"}}}},{"id":69,"type":"PrimitiveBoolean","pos":[1451.3182054438448,4674.625789498828],"size":[282.51029338612364,72.29914672352243],"flags":{},"order":34,"mode":0,"inputs":[{"label":"value","localized_name":"值","name":"value","type":"BOOLEAN","widget":{"name":"value"},"link":null}],"outputs":[{"label":"BOOLEAN","localized_name":"布尔","name":"BOOLEAN","type":"BOOLEAN","links":[84]}],"title":"Set true to use text prompt only","properties":{"cnr_id":"comfy-core","ver":"0.5.1","Node name for S&R":"PrimitiveBoolean","ue_properties":{"widget_ue_connectable":{},"version":"7.5.2","input_ue_unconnectable":{}}},"widgets_values":[false],"color":"#008181","bgcolor":"rgba(24,24,27,.9)"},{"id":91,"type":"LoadImage","pos":[860.6834854545715,3672.1271710749443],"size":[353.7636197975844,441.49045424953056],"flags":{},"order":35,"mode":0,"inputs":[{"localized_name":"图像","name":"image","type":"COMBO","widget":{"name":"image"},"link":null},{"localized_name":"选择文件上传","name":"upload","type":"IMAGEUPLOAD","widget":{"name":"upload"},"link":null}],"outputs":[{"label":"图像","localized_name":"图像","name":"IMAGE","type":"IMAGE","links":[120]},{"label":"遮罩","localized_name":"遮罩","name":"MASK","type":"MASK","links":null}],"properties":{"cnr_id":"comfy-core","ver":"0.8.2","Node name for S&R":"LoadImage","ue_properties":{"widget_ue_connectable":{},"input_ue_unconnectable":{},"version":"7.5.2"}},"widgets_values":["%ckpt.unet_name%_2025-12-04-020419_109_00001_.png","image"],"color":"#346434","bgcolor":"rgba(24,24,27,.9)"},{"id":30,"type":"CLIPTextEncode","pos":[1284.982476302133,4065.3912129014643],"size":[372.5105500950168,355.14172651903846],"flags":{},"order":39,"mode":0,"inputs":[{"label":"CLIP","localized_name":"clip","name":"clip","type":"CLIP","link":70},{"localized_name":"文本","name":"text","type":"STRING","widget":{"name":"text"},"link":null}],"outputs":[{"label":"条件","localized_name":"条件","name":"CONDITIONING","type":"CONDITIONING","links":[17]}],"properties":{"cnr_id":"comfy-core","ver":"0.3.56","Node name for S&R":"CLIPTextEncode","ue_properties":{"widget_ue_connectable":{},"version":"7.5.2","input_ue_unconnectable":{}},"enableTabs":false,"tabWidth":65,"tabXOffset":10,"hasSecondTab":false,"secondTabText":"Send Back","secondTabOffset":80,"secondTabWidth":65},"widgets_values":["Woman talking to the camera, and she says:   \"A workflow even simpler with  K Sampler and less complicated nodes\".\n\nThe scene: \nThe woman is outside in a snow winter landscape.\nIn the background ambient sound from cold wind.\n\nDynamic, cinematic video.\nThe woman gesticulate as she talks, with expressive body language."],"color":"#346434","bgcolor":"rgba(24,24,27,.9)"},{"id":70,"type":"ImageResizeKJv2","pos":[896.6667619034108,4170.306896335617],"size":[270,336],"flags":{"collapsed":false},"order":52,"mode":0,"inputs":[{"label":"image","localized_name":"image","name":"image","type":"IMAGE","link":120},{"label":"mask","localized_name":"mask","name":"mask","shape":7,"type":"MASK","link":null},{"label":"width","localized_name":"width","name":"width","type":"INT","widget":{"name":"width"},"link":86},{"label":"height","localized_name":"height","name":"height","type":"INT","widget":{"name":"height"},"link":85},{"label":"upscale_method","localized_name":"upscale_method","name":"upscale_method","type":"COMBO","widget":{"name":"upscale_method"},"link":null},{"label":"keep_proportion","localized_name":"keep_proportion","name":"keep_proportion","type":"COMBO","widget":{"name":"keep_proportion"},"link":null},{"label":"pad_color","localized_name":"pad_color","name":"pad_color","type":"STRING","widget":{"name":"pad_color"},"link":null},{"label":"crop_position","localized_name":"crop_position","name":"crop_position","type":"COMBO","widget":{"name":"crop_position"},"link":null},{"label":"divisible_by","localized_name":"divisible_by","name":"divisible_by","type":"INT","widget":{"name":"divisible_by"},"link":null},{"label":"device","localized_name":"device","name":"device","shape":7,"type":"COMBO","widget":{"name":"device"},"link":null}],"outputs":[{"label":"IMAGE","localized_name":"图像","name":"IMAGE","type":"IMAGE","links":[111,134]},{"label":"width","localized_name":"width","name":"width","type":"INT","links":[130]},{"label":"height","localized_name":"height","name":"height","type":"INT","links":[131]},{"label":"mask","localized_name":"mask","name":"mask","type":"MASK","links":null}],"properties":{"cnr_id":"comfyui-kjnodes","ver":"f710f2635dbadbaf1ccf7d25572daa7dfec80bfd","Node name for S&R":"ImageResizeKJv2","ue_properties":{"widget_ue_connectable":{"width":true,"height":true},"version":"7.5.2","input_ue_unconnectable":{}}},"widgets_values":[512,512,"nearest-exact","crop","0, 0, 0","center",32,"cpu"]},{"id":109,"type":"MarkdownNote","pos":[386.3961987955376,3407.904742044332],"size":[688.3443148648453,119.26988418238898],"flags":{"collapsed":false},"order":36,"mode":0,"inputs":[],"outputs":[],"title":"Frame Rate Note","properties":{"ue_properties":{"widget_ue_connectable":{},"input_ue_unconnectable":{},"version":"7.5.2"},"widget_ue_connectable":{}},"widgets_values":["# 镜像部署//QQ群：1046279436\n# 工作流转算力API镜像https://autodl.art/app/market/22?v=344\n"],"color":"#322","bgcolor":"#533"}],"links":[[2,27,0,2,0,"LATENT"],[15,6,0,7,1,"LATENT"],[17,30,0,10,0,"CONDITIONING"],[18,9,0,10,1,"CONDITIONING"],[38,34,0,24,1,"AUDIO"],[49,17,0,27,4,"INT"],[56,2,1,34,0,"LATENT"],[62,41,0,37,0,"CLIP"],[63,50,0,38,0,"VAE"],[66,47,0,46,0,"MODEL"],[67,49,0,48,0,"VAE"],[70,53,0,30,0,"CLIP"],[71,53,0,9,0,"CLIP"],[72,54,0,6,0,"VAE"],[75,57,0,3,1,"VAE"],[77,56,0,34,1,"VAE"],[78,62,0,58,0,"INT"],[79,61,0,59,0,"INT"],[80,63,0,60,0,"FLOAT"],[81,65,1,64,0,"INT"],[82,66,0,65,3,"INT"],[83,63,0,65,4,"FLOAT"],[84,69,0,68,0,"BOOLEAN"],[85,72,0,70,3,"INT"],[86,71,0,70,2,"INT"],[91,73,0,10,2,"FLOAT"],[92,74,0,75,3,"FLOAT"],[93,75,1,6,2,"INT"],[94,76,0,5,2,"INT"],[95,76,0,6,1,"INT"],[101,78,0,27,0,"MODEL"],[105,51,0,78,0,"MODEL"],[108,46,0,84,0,"MODEL"],[109,84,0,52,0,"MODEL"],[110,87,0,24,4,"FLOAT"],[111,70,0,85,1,"IMAGE"],[112,5,0,85,2,"LATENT"],[113,55,0,85,0,"VAE"],[114,85,0,7,0,"LATENT"],[115,88,0,85,4,"BOOLEAN"],[118,7,0,90,0,"LATENT"],[119,90,0,27,3,"LATENT"],[120,91,0,70,0,"IMAGE"],[121,2,0,3,0,"LATENT"],[122,10,0,94,0,"CONDITIONING"],[123,10,1,95,0,"CONDITIONING"],[128,97,0,27,2,"CONDITIONING"],[129,96,0,27,1,"CONDITIONING"],[130,70,1,98,0,"INT"],[131,70,2,99,0,"INT"],[132,100,0,5,0,"INT"],[133,101,0,5,1,"INT"],[134,70,0,103,0,"IMAGE"],[135,104,0,102,0,"IMAGE"],[140,3,0,24,0,"IMAGE"]],"groups":[{"id":1,"title":"Input Image","bounding":[819.8822923562072,3571.6996948174674,427.46690087832985,1008.5566329925573],"color":"#3f789e","font_size":24,"flags":{}},{"id":2,"title":"Models","bounding":[383.20628170247875,3569.213367751384,416.8903739443388,1005.8606902030651],"color":"#3f789e","font_size":24,"flags":{}},{"id":3,"title":"T2V - Text to video mode","bounding":[1420.9793271497413,4601.083647072022,337.92095075417024,163.30464980382385],"color":"#8AA","font_size":24,"flags":{}},{"id":4,"title":"Video Settings","bounding":[381.2194969633291,4597.072161830206,1016.8293036328371,167.52598620638764],"color":"#8A8","font_size":24,"flags":{}},{"id":5,"title":"Prompt","bounding":[1267.7236196201698,3977.6497987600465,416.01480550717724,597.9935921360138],"color":"#3f789e","font_size":24,"flags":{}},{"id":6,"title":"Decode","bounding":[2403.3049024400684,3580.611133948225,298.82307309952284,991.8579145303711],"color":"#3f789e","font_size":24,"flags":{}},{"id":7,"title":"LTX latent","bounding":[1709.9905102719304,3577.057467896224,326.6593533160908,994.5815291103863],"color":"#3f789e","font_size":24,"flags":{}},{"id":8,"title":"Sampler","bounding":[2055.4296692163093,3577.365327160922,329.69163303499636,993.1693675250726],"color":"#3f789e","font_size":24,"flags":{}},{"id":9,"title":"Lora","bounding":[1267.0313413916426,3573.067718479944,422.1360093164865,383.9548322113942],"color":"#3f789e","font_size":24,"flags":{}},{"id":10,"title":"Performance (optional)","bounding":[427.82920056774697,3916.384632951086,341.2496456909586,181.5675109415115],"color":"#3f789e","font_size":24,"flags":{}}],"config":{},"extra":{"workflowRendererVersion":"LG","ue_links":[],"ds":{"scale":0.876922695000001,"offset":[602.2884423289563,-2867.378190841322]},"frontendVersion":"1.37.11","VHS_latentpreview":false,"VHS_latentpreviewrate":0,"VHS_MetadataImage":false,"VHS_KeepIntermediate":false},"version":0.4}